llmling/__init__.py
llmling/__main__.py
llmling/cli/__init__.py
llmling/cli/config.py
llmling/cli/constants.py
llmling/cli/prompts.py
llmling/cli/resources.py
llmling/cli/tools.py
llmling/cli/utils.py
llmling/completions/__init__.py
llmling/completions/protocols.py
llmling/completions/types.py
llmling/config/__init__.py
llmling/config/base.py
llmling/config/llm_tools.py
llmling/config/manager.py
llmling/config/models.py
llmling/config/runtime.py
llmling/config/store.py
llmling/config/utils.py
llmling/config_resources/__init__.py
llmling/config_resources/basic.yml
llmling/config_resources/test.yml
llmling/config_resources/watch_examples.yml
llmling/config_resources/web_research.yml
llmling/core/__init__.py
llmling/core/baseregistry.py
llmling/core/chain.py
llmling/core/descriptors.py
llmling/core/exceptions.py
llmling/core/log.py
llmling/core/typedefs.py
llmling/core/utils.py
llmling/log.py
llmling/processors/__init__.py
llmling/processors/base.py
llmling/processors/jinjaprocessor.py
llmling/processors/registry.py
llmling/prompts/__init__.py
llmling/prompts/models.py
llmling/prompts/registry.py
llmling/prompts/utils.py
llmling/py.typed
llmling/resources/__init__.py
llmling/resources/base.py
llmling/resources/loaders/__init__.py
llmling/resources/loaders/callable.py
llmling/resources/loaders/cli.py
llmling/resources/loaders/path.py
llmling/resources/loaders/registry.py
llmling/resources/loaders/repository.py
llmling/resources/loaders/source.py
llmling/resources/loaders/text.py
llmling/resources/models.py
llmling/resources/registry.py
llmling/resources/watching/__init__.py
llmling/resources/watching/utils.py
llmling/resources/watching/watcher.py
llmling/testing/__init__.py
llmling/testing/processors.py
llmling/testing/tools.py
llmling/tools/__init__.py
llmling/tools/base.py
llmling/tools/code.py
llmling/tools/entry_points.py
llmling/tools/exceptions.py
llmling/tools/importing.py
llmling/tools/openapi.py
llmling/tools/registry.py
llmling/tools/toolsets.py
llmling-2.0.10.dist-info/licenses/LICENSE
llmling-2.0.10.dist-info/WHEEL
llmling-2.0.10.dist-info/entry_points.txt
llmling-2.0.10.dist-info/METADATA
llmling-2.0.10.dist-info/RECORD
