Metadata-Version: 2.4
Name: llmling
Version: 2.0.10
Summary: A backend for pydantic-AI agents and MCP servers.
Keywords: 
Author: Philipp Temminghoff
Author-email: Philipp Temminghoff <philipptemminghoff@googlemail.com>
License-Expression: MIT
License-File: LICENSE
Classifier: Development Status :: 4 - Beta
Classifier: Framework :: Pydantic
Classifier: Framework :: Pydantic :: 2
Classifier: Intended Audience :: Developers
Classifier: Operating System :: OS Independent
Classifier: Programming Language :: Python :: 3
Classifier: Programming Language :: Python :: 3 :: Only
Classifier: Programming Language :: Python :: 3.12
Classifier: Programming Language :: Python :: 3.13
Classifier: Programming Language :: Python :: 3.14
Classifier: Topic :: Documentation
Classifier: Topic :: Software Development
Classifier: Topic :: Utilities
Classifier: Typing :: Typed
Requires-Dist: depkit>=0.3.5
Requires-Dist: epregistry>=1.2.0
Requires-Dist: fsspec
Requires-Dist: httpx
Requires-Dist: jinja2>=3.1.4
Requires-Dist: pathspec
Requires-Dist: platformdirs>=4.3.6
Requires-Dist: promptantic>=0.4.3
Requires-Dist: psygnal>=0.11.1
Requires-Dist: pydantic
Requires-Dist: schemez>=1.2.0
Requires-Dist: typer
Requires-Dist: universal-pathlib>=0.2.5
Requires-Dist: upathtools[httpx]
Requires-Dist: yamling>=1.5.0
Requires-Dist: llmling-agent ; extra == 'agent'
Requires-Dist: llmling-agent ; extra == 'all'
Requires-Dist: mcp-server-llmling ; extra == 'all'
Requires-Dist: watchfiles ; extra == 'all'
Requires-Dist: pygit2 ; extra == 'all'
Requires-Dist: gitpython ; extra == 'all'
Requires-Dist: fsspec[http,github] ; extra == 'all'
Requires-Dist: fsspec[http,github] ; extra == 'fsspec-extras'
Requires-Dist: pygit2 ; extra == 'git'
Requires-Dist: gitpython ; extra == 'git'
Requires-Dist: mcp-server-llmling ; extra == 'server'
Requires-Dist: watchfiles ; extra == 'watch-files'
Requires-Python: >=3.13
Project-URL: Code coverage, https://app.codecov.io/gh/phil65/llmling
Project-URL: Discussions, https://github.com/phil65/llmling/discussions
Project-URL: Documentation, https://phil65.github.io/llmling/
Project-URL: Issues, https://github.com/phil65/llmling/issues
Project-URL: Source, https://github.com/phil65/llmling
Provides-Extra: agent
Provides-Extra: all
Provides-Extra: fsspec-extras
Provides-Extra: git
Provides-Extra: server
Provides-Extra: watch-files
